langchain_executor
